setup.py
zenpad/__init__.py
zenpad/filepad.py
zenpad/py2exe_setup.py
zenpad/trans.py
zenpad/utils.py
zenpad/zenpad.py
zenpad.egg-info/PKG-INFO
zenpad.egg-info/SOURCES.txt
zenpad.egg-info/dependency_links.txt
zenpad.egg-info/entry_points.txt
zenpad.egg-info/not-zip-safe
zenpad.egg-info/requires.txt
zenpad.egg-info/top_level.txt
zenpad/ui/__init__.py
zenpad/ui/add_pad.py
zenpad/ui/mainform.py
zenpad/ui/resources_rc.py
zenpad/ui/settings.py
zenpad/ui/sync.py