Metadata-Version: 1.0
Name: zenpad
Version: 0.0.11
Summary: Tree-structured notepad
Home-page: http://zenpad.ru/
Author: Imbolc
Author-email: imbolc@imbolc.name
License: UNKNOWN
Platform: UNKNOWN
Classifier: Programming Language :: Python
Classifier: License :: OSI Approved :: MIT License
Classifier: Development Status :: 4 - Beta
Classifier: Environment :: X11 Applications :: Qt
Classifier: Intended Audience :: End Users/Desktop
Classifier: Natural Language :: Russian
Classifier: Topic :: Text Editors
